{"timestamp":"2026-06-21T18:14:20.415Z","npmScanResults":[{"name":"react","files":27,"findings":1315,"ms":2329,"byCat":{"missing-skip-links":1068,"dockerfile":49,"aria-labels":1,"missing-aria-label":1,"console-log":61,"cruft":119,"ai-incomplete-code":3,"empty-catch-block":6,"ai-template":5,"prototype-pollution":2}},{"name":"lodash","files":1051,"findings":14230,"ms":24513,"byCat":{"missing-skip-links":13128,"dockerfile":392,"ci-cd":2,"phone-number":10,"inefficient-data-structures":7,"prototype-pollution":21,"unreachable-code":23,"cruft":17,"placeholder-code":462,"ai-buzzwords":2,"api-versioning":4,"empty-catch-block":14,"mock-stub":4,"console-log":108,"n-plus-one-query":16,"insecure-flag":5,"injection":3,"timeout":4,"typescript-any":2,"auto-confirm":4,"synchronous-api":2}},{"name":"express","files":10,"findings":840,"ms":1280,"byCat":{"missing-skip-links":795,"dockerfile":10,"ci-cd":4,"github-workflow":3,"console-log":2,"hardcoded-url":6,"cruft":13,"ai-safety-bypass":1,"input-validation":5,"api-versioning":1}},{"name":"vue","files":37,"findings":69,"ms":311,"byCat":{"missing-skip-links":50,"dockerfile":15,"ai-overuse":1,"typescript-any":2,"cruft":1}},{"name":"axios","files":85,"findings":4625,"ms":6777,"byCat":{"missing-skip-links":3388,"ci-cd":24,"github-workflow":16,"dockerfile":343,"ai-emoji":15,"cruft":74,"timeout":23,"ci-bypass":3,"prototype-pollution":18,"circleci-personal-token":157,"aria-labels":201,"missing-alt-text":201,"ai-safety-bypass":9,"hardcoded-url":4,"console-log":69,"unreachable-code":5,"deprecated-function":2,"authentication":2,"typescript-any":55,"api-versioning":1,"insecure-flag":4,"form-labels":1,"ai-overuse":1,"ai-template":1,"bundler-optimization":2,"empty-catch-block":1,"hardcoded-secrets":1,"inefficient-data-structures":2,"auto-confirm":1,"phone-number":1}},{"name":"typescript","files":140,"findings":0,"ms":120111,"byCat":{}}],"byPattern":{"missing-skip-links":18429,"dockerfile":809,"aria-labels":202,"missing-aria-label":1,"console-log":240,"cruft":224,"ai-incomplete-code":3,"empty-catch-block":21,"ai-template":6,"prototype-pollution":41,"ci-cd":30,"phone-number":11,"inefficient-data-structures":9,"unreachable-code":28,"placeholder-code":462,"ai-buzzwords":2,"api-versioning":6,"mock-stub":4,"n-plus-one-query":16,"insecure-flag":9,"injection":3,"timeout":27,"typescript-any":59,"auto-confirm":5,"synchronous-api":2,"github-workflow":19,"hardcoded-url":10,"ai-safety-bypass":10,"input-validation":5,"ai-overuse":2,"ai-emoji":15,"ci-bypass":3,"circleci-personal-token":157,"missing-alt-text":201,"deprecated-function":2,"authentication":2,"form-labels":1,"bundler-optimization":2,"hardcoded-secrets":1},"totalFindings":21079,"totalFiles":1350,"totalScanMs":155321}